monochromap/__init__.py
monochromap/monochromap.py
monochromap-0.3.1.dist-info/LICENSE.txt
monochromap-0.3.1.dist-info/METADATA
monochromap-0.3.1.dist-info/WHEEL
monochromap-0.3.1.dist-info/top_level.txt
monochromap-0.3.1.dist-info/RECORD
