Metadata-Version: 2.1
Name: monochromap
Version: 0.3.1
Summary: A highly opinionated library to plot map on top of stamen toner tile style
Author-email: M Iqbal Tawakal <mit.iqi@gmail.com>
Project-URL: Repository, https://github.com/mitbal/monochromap.git
Keywords: map,visualization,data science
Classifier: License :: OSI Approved :: MIT License
Classifier: Programming Language :: Python :: 3
Classifier: Operating System :: OS Independent
Requires-Python: >=3.9
License-File: LICENSE.txt
Requires-Dist: pillow >=10.3.0
Requires-Dist: requests >=2.31.0
